AgentMix/__init__.py
AgentMix/main.py
AgentMix-1.7.dist-info/METADATA
AgentMix-1.7.dist-info/WHEEL
AgentMix-1.7.dist-info/entry_points.txt
AgentMix-1.7.dist-info/top_level.txt
AgentMix-1.7.dist-info/RECORD
