Metadata-Version: 2.1
Name: AgentMix
Version: 1.7
Requires-Dist: httpx
Requires-Dist: asyncio
Requires-Dist: colorama
Requires-Dist: beautifulsoup4
